split_alphanumeric.py
split_alphanumeric-0.3.dist-info/METADATA
split_alphanumeric-0.3.dist-info/WHEEL
split_alphanumeric-0.3.dist-info/top_level.txt
split_alphanumeric-0.3.dist-info/RECORD
